langchain_azure_ai/__init__.py
langchain_azure_ai/_api/base.py
langchain_azure_ai/_resources.py
langchain_azure_ai/agents/__init__.py
langchain_azure_ai/agents/agent_service.py
langchain_azure_ai/agents/prebuilt/__init__.py
langchain_azure_ai/agents/prebuilt/declarative.py
langchain_azure_ai/agents/prebuilt/tools.py
langchain_azure_ai/callbacks/__init__.py
langchain_azure_ai/callbacks/tracers/__init__.py
langchain_azure_ai/callbacks/tracers/_semantic_conventions_gen_ai.py
langchain_azure_ai/callbacks/tracers/inference_tracing.py
langchain_azure_ai/chat_message_histories/__init__.py
langchain_azure_ai/chat_message_histories/cosmos_db.py
langchain_azure_ai/chat_models/__init__.py
langchain_azure_ai/chat_models/inference.py
langchain_azure_ai/embeddings/__init__.py
langchain_azure_ai/embeddings/inference.py
langchain_azure_ai/query_constructors/__init__.py
langchain_azure_ai/query_constructors/cosmosdb_no_sql.py
langchain_azure_ai/retrievers/__init__.py
langchain_azure_ai/retrievers/azure_ai_search.py
langchain_azure_ai/tools/__init__.py
langchain_azure_ai/tools/ai_services/document_intelligence.py
langchain_azure_ai/tools/ai_services/image_analysis.py
langchain_azure_ai/tools/ai_services/text_analytics_health.py
langchain_azure_ai/tools/logic_apps.py
langchain_azure_ai/utils/env.py
langchain_azure_ai/utils/math.py
langchain_azure_ai/utils/utils.py
langchain_azure_ai/vectorstores/__init__.py
langchain_azure_ai/vectorstores/azure_cosmos_db_mongo_vcore.py
langchain_azure_ai/vectorstores/azure_cosmos_db_no_sql.py
langchain_azure_ai/vectorstores/azuresearch.py
langchain_azure_ai/vectorstores/cache.py
langchain_azure_ai/vectorstores/utils.py
langchain_azure_ai-1.0.3.dist-info/LICENSE
langchain_azure_ai-1.0.3.dist-info/METADATA
langchain_azure_ai-1.0.3.dist-info/WHEEL
langchain_azure_ai-1.0.3.dist-info/RECORD
