Metadata-Version: 2.3
Name: langchain-azure-ai
Version: 1.0.3
Summary: An integration package to support Azure AI Foundry capabilities in LangChain/LangGraph ecosystem.
License: MIT License
Requires-Python: >=3.10.0,<4.0
Classifier: License :: Other/Proprietary License
Classifier: Programming Language :: Python :: 3
Classifier: Programming Language :: Python :: 3.10
Classifier: Programming Language :: Python :: 3.11
Classifier: Programming Language :: Python :: 3.12
Classifier: Programming Language :: Python :: 3.13
Provides-Extra: opentelemetry
Provides-Extra: tools
Requires-Dist: aiohttp (>=3.10,<4.0)
Requires-Dist: azure-ai-agents (>=1.2.0b3,<1.3.0)
Requires-Dist: azure-ai-documentintelligence (>=1.0.2,<2.0.0) ; extra == "tools"
Requires-Dist: azure-ai-inference[opentelemetry] (>=1.0.0b9,<2.0)
Requires-Dist: azure-ai-projects (>=1.0,<2.0)
Requires-Dist: azure-ai-textanalytics (>=5.3.0,<6.0.0) ; extra == "tools"
Requires-Dist: azure-ai-vision-imageanalysis (>=1.0.0,<2.0.0) ; extra == "tools"
Requires-Dist: azure-core (>=1.32,<2.0)
Requires-Dist: azure-cosmos (>=4.14.0b1,<5.0)
Requires-Dist: azure-identity (>=1.15,<2.0)
Requires-Dist: azure-mgmt-logic (>=10.0.0,<11.0.0) ; extra == "tools"
Requires-Dist: azure-monitor-opentelemetry (>=1.6,<2.0) ; extra == "opentelemetry"
Requires-Dist: azure-search-documents (>=11.4,<12.0)
Requires-Dist: langchain (>=1.0.0,<2.0.0)
Requires-Dist: langchain-openai (>=1.0.0,<2.0.0)
Requires-Dist: numpy (>=1.26.2) ; python_version < "3.13"
Requires-Dist: numpy (>=2.1.0) ; python_version >= "3.13"
Requires-Dist: opentelemetry-api (>=1.37) ; extra == "opentelemetry"
Requires-Dist: opentelemetry-instrumentation (>=0.58b0) ; extra == "opentelemetry"
Requires-Dist: opentelemetry-instrumentation-threading (>=0.58b0) ; extra == "opentelemetry"
Requires-Dist: opentelemetry-semantic-conventions (>=0.58b0) ; extra == "opentelemetry"
Requires-Dist: opentelemetry-semantic-conventions-ai (>=0.4.2,<0.5.0) ; extra == "opentelemetry"
Requires-Dist: six (>=1.17.0,<2.0.0)
Project-URL: Repository, https://github.com/langchain-ai/langchain-azure
Project-URL: Release Notes, https://github.com/langchain-ai/langchain-azure/releases
Project-URL: Source Code, https://github.com/langchain-ai/langchain-azure/tree/main/libs/azure-ai
